Metadata-Version: 1.1
Name: rh.osxdiskutils
Version: 0.1
Summary: Utilities to work with disks on macOS
Home-page: http://github.com/rharke/rh.osxdiskutils
Author: Ranger Harke
Author-email: ranger.harke@gmail.com
License: MIT
Platform: UNKNOWN
Classifier: Development Status :: 3 - Alpha
Classifier: Environment :: MacOS X
Classifier: License :: OSI Approved :: MIT License
Classifier: Natural Language :: English
Classifier: Operating System :: MacOS :: MacOS X
Classifier: Programming Language :: Python
Classifier: Topic :: Software Development :: Libraries :: Python Modules
